README.md
setup.py
OliveUtils/__init__.py
OliveUtils.egg-info/PKG-INFO
OliveUtils.egg-info/SOURCES.txt
OliveUtils.egg-info/dependency_links.txt
OliveUtils.egg-info/top_level.txt
OliveUtils/stats/__init__.py
OliveUtils/stats/funcs.py