Metadata-Version: 1.0
Name: OliveUtils
Version: 0.0.5
Summary: Olive's DS utils
Home-page: UNKNOWN
Author: Yuval Cohen
Author-email: UNKNOWN
License: UNKNOWN
Platform: UNKNOWN
